CHANGES.rst
LICENSE.txt
MANIFEST.in
README.rst
setup.py
src/newt/__init__.py
src/newt.qbe.egg-info/PKG-INFO
src/newt.qbe.egg-info/SOURCES.txt
src/newt.qbe.egg-info/dependency_links.txt
src/newt.qbe.egg-info/entry_points.txt
src/newt.qbe.egg-info/namespace_packages.txt
src/newt.qbe.egg-info/not-zip-safe
src/newt.qbe.egg-info/requires.txt
src/newt.qbe.egg-info/top_level.txt
src/newt/qbe/__init__.py
src/newt/qbe/tests.py